{
    "type": "Feature",
    "geometry": {
        "type": "LineString",
        "coordinates": [
            [
                139.6748373,
                35.5080606
            ],
            [
                139.6747957,
                35.5089689
            ],
            [
                139.674726,
                35.5099842
            ],
            [
                139.6746777,
                35.5106632
            ],
            [
                139.6746321,
                35.511351
            ],
            [
                139.6746093,
                35.5119306
            ],
            [
                139.6745369,
                35.512864
            ],
            [
                139.6744672,
                35.5136816
            ],
            [
                139.6743223,
                35.5142089
            ],
            [
                139.6742714,
                35.5149206
            ],
            [
                139.6740032,
                35.5158179
            ],
            [
                139.6731247,
                35.5178013
            ],
            [
                139.672882,
                35.5184355
            ],
            [
                139.6723952,
                35.520337
            ],
            [
                139.6721001,
                35.5214482
            ],
            [
                139.6717595,
                35.5227951
            ],
            [
                139.6713035,
                35.5237349
            ],
            [
                139.6706048,
                35.5249683
            ],
            [
                139.6697934,
                35.5262999
            ],
            [
                139.6687755,
                35.5280363
            ],
            [
                139.6678837,
                35.529584
            ],
            [
                139.6674881,
                35.5302214
            ],
            [
                139.6669288,
                35.5310203
            ],
            [
                139.6661148,
                35.5319458
            ],
            [
                139.6652162,
                35.532833
            ],
            [
                139.6647857,
                35.532331
            ],
            [
                139.6641366,
                35.531555
            ],
            [
                139.6629498,
                35.5301733
            ],
            [
                139.6621813,
                35.5292729
            ],
            [
                139.6615456,
                35.5282241
            ],
            [
                139.6614182,
                35.52839
            ],
            [
                139.661138,
                35.5286465
            ],
            [
                139.6607155,
                35.5285035
            ],
            [
                139.6604647,
                35.5283845
            ],
            [
                139.6601978,
                35.5280494
            ]
        ]
    },
    "properties": {
        "route_id": 14
    }
}